tekhsi/__init__.py
tekhsi/_tek_highspeed_server_pb2.py
tekhsi/_tek_highspeed_server_pb2.pyi
tekhsi/_tek_highspeed_server_pb2_grpc.py
tekhsi/helpers/__init__.py
tekhsi/helpers/constants.py
tekhsi/helpers/functions.py
tekhsi/tek_hsi_connect.py
tekhsi-1.0.0.dist-info/LICENSE.md
tekhsi-1.0.0.dist-info/METADATA
tekhsi-1.0.0.dist-info/WHEEL
tekhsi-1.0.0.dist-info/RECORD
