Metadata-Version: 2.1
Name: TekHSI
Version: 1.0.0
Summary: Transfer waveforms from Tektronix Oscilloscopes using the High-Speed Interface.
Home-page: https://pypi.org/project/TekHSI/
License: Apache-2.0
Keywords: Tektronix,Test & Measurement
Author: Tektronix
Author-email: opensource@tektronix.com
Maintainer: Tektronix
Maintainer-email: opensource@tektronix.com
Requires-Python: >=3.8,<4.0
Classifier: Development Status :: 4 - Beta
Classifier: Intended Audience :: Developers
Classifier: Intended Audience :: Science/Research
Classifier: License :: OSI Approved :: Apache Software License
Classifier: Operating System :: OS Independent
Classifier: Programming Language :: Python :: 3
Classifier: Programming Language :: Python :: 3.8
Classifier: Programming Language :: Python :: 3.9
Classifier: Programming Language :: Python :: 3.10
Classifier: Programming Language :: Python :: 3.11
Classifier: Programming Language :: Python :: 3.12
Classifier: Topic :: Scientific/Engineering
Classifier: Topic :: Scientific/Engineering :: Interface Engine/Protocol Translator
Classifier: Topic :: System :: Hardware :: Hardware Drivers
Requires-Dist: grpcio (>=1.51.3,<2.0.0)
Requires-Dist: numpy (>=1.24,<2.0) ; python_version >= "3.8" and python_version < "3.12"
Requires-Dist: numpy (>=1.26,<2.0) ; python_version >= "3.9" and python_version < "4.0"
Requires-Dist: protobuf (>=5.28.1,<6.0.0)
Requires-Dist: python-dateutil (>=2.8.2,<3.0.0)
Requires-Dist: tm_data_types (>=0.1.0,<0.2.0)
Requires-Dist: typing_extensions (>=4.12.0,<5.0.0)
Project-URL: Bug Tracker, https://github.com/tektronix/TekHSI/issues
Project-URL: Changelog, https://github.com/tektronix/TekHSI/blob/main/CHANGELOG.md
Project-URL: Documentation, https://TekHSI.readthedocs.io
Project-URL: Repository, https://github.com/tektronix/TekHSI
